README.md
setup.py
monoensemble/__init__.py
monoensemble/_mono_gradient_boosting.c
monoensemble/mono_forest.py
monoensemble/mono_gradient_boosting.py
monoensemble/setup.py
monoensemble/version.py
monoensemble.egg-info/PKG-INFO
monoensemble.egg-info/SOURCES.txt
monoensemble.egg-info/dependency_links.txt
monoensemble.egg-info/not-zip-safe
monoensemble.egg-info/requires.txt
monoensemble.egg-info/top_level.txt
monoensemble/data/boston.csv
monoensemble/tests/__init__.py
monoensemble/tests/test_mono_forest.py
monoensemble/tests/test_mono_gradient_boosting.py