Metadata-Version: 1.1
Name: monoensemble
Version: 0.8
Summary: 
